privex/__init__.py
privex/steemengine/SteemEngineHistory.py
privex/steemengine/SteemEngineToken.py
privex/steemengine/__init__.py
privex/steemengine/exceptions.py
privex/steemengine/objects.py
privex_steemengine-2.4.0.dist-info/LICENSE
privex_steemengine-2.4.0.dist-info/METADATA
privex_steemengine-2.4.0.dist-info/WHEEL
privex_steemengine-2.4.0.dist-info/top_level.txt
privex_steemengine-2.4.0.dist-info/RECORD
