Metadata-Version: 2.1
Name: privex-steemengine
Version: 2.4.0
Summary: A small library for querying and interacting with the Steem/HiveEngine network (https://steem-engine.com / https://hive-engine.com)
Home-page: https://github.com/Privex/python-steemengine
Author: Chris (Someguy123) @ Privex
Author-email: chris@privex.io
License: MIT
Platform: UNKNOWN
Classifier: Programming Language :: Python :: 3
Classifier: Programming Language :: Python :: 3.7
Classifier: Programming Language :: Python :: 3.8
Classifier: Programming Language :: Python :: 3.9
Classifier: License :: OSI Approved :: MIT License
Classifier: Operating System :: OS Independent
Requires-Dist: privex-jsonrpc (>=1.0.0)
Requires-Dist: beem (>=0.24.15)
Requires-Dist: requests (>=2.20.1)
Requires-Dist: privex-helpers (>=3.0.0)
Provides-Extra: dev
Requires-Dist: pytest ; extra == 'dev'
Requires-Dist: pytest-cov ; extra == 'dev'
Requires-Dist: pytest-asyncio ; extra == 'dev'
Requires-Dist: coverage ; extra == 'dev'
Requires-Dist: codecov ; extra == 'dev'
Requires-Dist: jupyter ; extra == 'dev'
